marteo_cli/__init__.py
marteo_cli/main.py
marteo_cli/version.py
marteo_cli/commands/__init__.py
marteo_cli/commands/start.py
marteo_cli/templates/blank/.gitignore
marteo_cli/templates/blank/README.md
marteo_cli/templates/blank/main.cpp
marteo_cli/templates/cmake/.gitignore
marteo_cli/templates/cmake/CMakeLists.txt
marteo_cli/templates/cmake/README.md
marteo_cli/templates/cmake/main.cpp
marteo_cli/templates/header/.gitignore
marteo_cli/templates/header/README.md
marteo_cli/templates/header/greeter.cpp
marteo_cli/templates/header/greeter.h
marteo_cli/templates/header/main.cpp
marteo_cli/templates/hmake/.gitignore
marteo_cli/templates/hmake/CMakeLists.txt
marteo_cli/templates/hmake/README.md
marteo_cli/templates/hmake/greeter.cpp
marteo_cli/templates/hmake/greeter.h
marteo_cli/templates/hmake/main.cpp
marteocli-0.1.2.dist-info/licenses/LICENSE
marteocli-0.1.2.dist-info/METADATA
marteocli-0.1.2.dist-info/WHEEL
marteocli-0.1.2.dist-info/entry_points.txt
marteocli-0.1.2.dist-info/top_level.txt
marteocli-0.1.2.dist-info/RECORD
