Metadata-Version: 2.4
Name: marteocli
Version: 0.1.2
Summary: Uma ferramenta para iniciar projetos C++ com templates pré-definidos.
Author-email: BomfInit Labs <dev@bomfinitlabs.com.br>, devjhones <devjhones@outlook.com>
License: MIT License
Project-URL: Homepage, https://github.com/BomfInit-Labs/MarteoCLI
Project-URL: Repository, https://github.com/BomfInit-Labs/MarteoCLI
Project-URL: Bug Tracker, https://github.com/BomfInit-Labs/MarteoCLI/issues
Classifier: Development Status :: 4 - Beta
Classifier: Intended Audience :: Developers
Classifier: License :: OSI Approved :: MIT License
Classifier: Programming Language :: Python :: 3
Classifier: Programming Language :: Python :: 3.10
Classifier: Programming Language :: Python :: 3.11
Classifier: Topic :: Software Development :: Build Tools
Classifier: Topic :: Software Development :: Code Generators
Classifier: Environment :: Console
Classifier: Operating System :: OS Independent
Requires-Python: >=3.10
License-File: LICENSE
Requires-Dist: rich>=14.2.0
Requires-Dist: typer>=0.20.1
Provides-Extra: test
Requires-Dist: pytest>=7.0.0; extra == "test"
Requires-Dist: pytest-cov>=3.0.0; extra == "test"
Requires-Dist: coverage>=7.13.0; extra == "test"
Requires-Dist: pip-audit>=2.10.0; extra == "test"
Requires-Dist: pre-commit>=4.5.1; extra == "test"
Requires-Dist: ruff>=0.14.10; extra == "test"
Dynamic: license-file
